chaos_filler/__init__.py
chaos_filler/main.py
chaos_filler/src/__init__.py
chaos_filler/src/filler.py
chaos_filler-0.1.2.dist-info/entry_points.txt
chaos_filler-0.1.2.dist-info/WHEEL
chaos_filler-0.1.2.dist-info/METADATA
chaos_filler-0.1.2.dist-info/RECORD
