Metadata-Version: 2.1
Name: chaos-filler
Version: 0.1.2
Summary: chaos filler
Author: chaos team
Requires-Python: >=3.8,<4.0
Classifier: Programming Language :: Python :: 3
Classifier: Programming Language :: Python :: 3.10
Classifier: Programming Language :: Python :: 3.8
Classifier: Programming Language :: Python :: 3.9
